.gitignore
AUTHORS
COPYING
INSTALL
Makefile
README
TODO
ez_setup.py
setup.py
debian/changelog
debian/compat
debian/control
debian/copyright
debian/pycompat
debian/pyversions
debian/rules
doc/HOWTO.txt
doc/README
doc/example.xml
doc/lobbyists.rng
lobbyists/__init__.py
lobbyists/benchmark.py
lobbyists/lobbyists.py
lobbyists/lobbyists.sql
lobbyists/util.py
lobbyists.egg-info/PKG-INFO
lobbyists.egg-info/SOURCES.txt
lobbyists.egg-info/dependency_links.txt
lobbyists.egg-info/entry_points.txt
lobbyists.egg-info/top_level.txt
lobbyists/tests/__init__.py
lobbyists/tests/test_db.py
lobbyists/tests/test_doctests.py
lobbyists/tests/test_import_affiliated_orgs.py
lobbyists/tests/test_import_clients.py
lobbyists/tests/test_import_filings.py
lobbyists/tests/test_import_foreign_entities.py
lobbyists/tests/test_import_govt_entites.py
lobbyists/tests/test_import_issues.py
lobbyists/tests/test_import_lobbyists.py
lobbyists/tests/test_import_registrants.py
lobbyists/tests/test_parse_affiliated_orgs.py
lobbyists/tests/test_parse_clients.py
lobbyists/tests/test_parse_filings.py
lobbyists/tests/test_parse_foreign_entities.py
lobbyists/tests/test_parse_govt_entities.py
lobbyists/tests/test_parse_issues.py
lobbyists/tests/test_parse_lobbyists.py
lobbyists/tests/test_parse_registrants.py
lobbyists/tests/util.py
lobbyists/tests/data/affiliated_org_country.xml
lobbyists/tests/data/affiliated_org_name.xml
lobbyists/tests/data/affiliated_orgs.xml
lobbyists/tests/data/affiliated_orgs_dup.xml
lobbyists/tests/data/affiliated_orgs_slightly_different.xml
lobbyists/tests/data/amounts.xml
lobbyists/tests/data/client_contact_name.xml
lobbyists/tests/data/client_country.xml
lobbyists/tests/data/client_description.xml
lobbyists/tests/data/client_id.xml
lobbyists/tests/data/client_name.xml
lobbyists/tests/data/client_state.xml
lobbyists/tests/data/client_state_or_local_gov.xml
lobbyists/tests/data/client_status.xml
lobbyists/tests/data/clients.xml
lobbyists/tests/data/clients_different_contact_name.xml
lobbyists/tests/data/clients_different_description.xml
lobbyists/tests/data/clients_different_senate_id.xml
lobbyists/tests/data/clients_different_status.xml
