Metadata-Version: 1.0
Name: lobbyists
Version: 0.10
Summary: Parse Senate LD-1/LD-2 lobbying disclosure XML documents
Home-page: http://github.com/dhess/lobbyists/
Author: Drew Hess
Author-email: dhess-src@bothan.net
License: GPLv3
Keywords: lobbyists government parser
Platform: UNKNOWN
Classifier: Development Status :: 4 - Beta
Classifier: Intended Audience :: Developers
Classifier: License :: OSI Approved :: GNU General Public License (GPL)
Classifier: Operating System :: OS Independent
Classifier: Programming Language :: Python
Classifier: Topic :: Database
Classifier: Topic :: Software Development :: Libraries :: Python Modules
